MANIFEST.in
README.rst
compile_messages.py
conftest.py
example-mwlib.config
ez_setup.py
make_messages.py
setup.cfg
setup.py
tox.ini
mwlib/__init__.py
mwlib.rl.egg-info/PKG-INFO
mwlib.rl.egg-info/SOURCES.txt
mwlib.rl.egg-info/dependency_links.txt
mwlib.rl.egg-info/entry_points.txt
mwlib.rl.egg-info/namespace_packages.txt
mwlib.rl.egg-info/not-zip-safe
mwlib.rl.egg-info/requires.txt
mwlib.rl.egg-info/top_level.txt
mwlib/fonts/__init__.py
mwlib/fonts/freefont/AUTHORS
mwlib/fonts/freefont/COPYING
mwlib/fonts/freefont/CREDITS
mwlib/fonts/freefont/ChangeLog
mwlib/fonts/freefont/FreeMono.ttf
mwlib/fonts/freefont/FreeMonoBold.ttf
mwlib/fonts/freefont/FreeMonoBoldOblique.ttf
mwlib/fonts/freefont/FreeMonoOblique.ttf
mwlib/fonts/freefont/FreeSans.ttf
mwlib/fonts/freefont/FreeSansBold.ttf
mwlib/fonts/freefont/FreeSansBoldOblique.ttf
mwlib/fonts/freefont/FreeSansOblique.ttf
mwlib/fonts/freefont/FreeSerif.ttf
mwlib/fonts/freefont/FreeSerifBold.ttf
mwlib/fonts/freefont/FreeSerifBoldItalic.ttf
mwlib/fonts/freefont/FreeSerifItalic.ttf
mwlib/fonts/freefont/INSTALL
mwlib/fonts/freefont/README
mwlib/rl/__init__.py
mwlib/rl/_version.py
mwlib/rl/create_collection.py
mwlib/rl/customflowables.py
mwlib/rl/customnodetransformer.py
mwlib/rl/debughelper.py
mwlib/rl/fontconfig.py
mwlib/rl/formatter.py
mwlib/rl/pagetemplates.py
mwlib/rl/pdfmessages.py
mwlib/rl/pdfstyles.py
mwlib/rl/rlsourceformatter.py
mwlib/rl/rltables.py
mwlib/rl/rlwriter.py
mwlib/rl/toc.py
mwlib/rl/wikipedia_logo.png
mwlib/rl/locale/aeb/LC_MESSAGES/mwlib.rl.po
mwlib/rl/locale/af/LC_MESSAGES/mwlib.rl.po
mwlib/rl/locale/ar/LC_MESSAGES/mwlib.rl.po
mwlib/rl/locale/arc/LC_MESSAGES/mwlib.rl.po
mwlib/rl/locale/arz/LC_MESSAGES/mwlib.rl.po
mwlib/rl/locale/ast/LC_MESSAGES/mwlib.rl.po
mwlib/rl/locale/az/LC_MESSAGES/mwlib.rl.po
mwlib/rl/locale/ba/LC_MESSAGES/mwlib.rl.po
mwlib/rl/locale/bar/LC_MESSAGES/mwlib.rl.po
mwlib/rl/locale/be-tarask/LC_MESSAGES/mwlib.rl.po
mwlib/rl/locale/bg/LC_MESSAGES/mwlib.rl.po
mwlib/rl/locale/bn/LC_MESSAGES/mwlib.rl.po
mwlib/rl/locale/bpy/LC_MESSAGES/mwlib.rl.po
mwlib/rl/locale/br/LC_MESSAGES/mwlib.rl.po
mwlib/rl/locale/bs/LC_MESSAGES/mwlib.rl.po
mwlib/rl/locale/ca/LC_MESSAGES/mwlib.rl.po
mwlib/rl/locale/ckb/LC_MESSAGES/mwlib.rl.po
