Metadata-Version: 1.0
Name: mwlib.rl
Version: 0.12.11
Summary: generate pdfs from mediawiki markup
Home-page: http://code.pediapress.com/
Author: pediapress.com
Author-email: info@pediapress.com
License: BSD License
Platform: UNKNOWN
